jpy_datareader/__init__.py
jpy_datareader/_utils.py
jpy_datareader/base.py
jpy_datareader/data.py
jpy_datareader/estat.py
jpy_datareader/gbizinfo.py
jpy_datareader-0.1.1.dist-info/licenses/LICENSE
jpy_datareader-0.1.1.dist-info/METADATA
jpy_datareader-0.1.1.dist-info/WHEEL
jpy_datareader-0.1.1.dist-info/top_level.txt
jpy_datareader-0.1.1.dist-info/RECORD
