Metadata-Version: 2.4
Name: jpy-datareader
Version: 0.1.1
Summary: A Remote data access to government data for pandas.
Project-URL: Homepage, https://github.com/well-living/jpy-datareader
Project-URL: Bug Tracker, https://github.com/well-living/jpy-datareader/issues
Project-URL: Source, https://github.com/well-living/jpy-datareader
Requires-Python: >=3.12
License-File: LICENSE
Requires-Dist: numpy
Requires-Dist: pandas
Requires-Dist: requests
Requires-Dist: python-dotenv
Dynamic: license-file
